[
    {
        "id": "27223b680e789dbf",
        "type": "tab",
        "label": "Flow 1",
        "disabled": false,
        "info": "",
        "env": []
    },
    {
        "id": "d2b2d8ed31f03335",
        "type": "mqtt in",
        "z": "27223b680e789dbf",
        "name": "",
        "topic": "esp32/data",
        "qos": "0",
        "datatype": "auto-detect",
        "broker": "355e398b737d8c0a",
        "nl": false,
        "rap": true,
        "rh": 0,
        "inputs": 0,
        "x": 200,
        "y": 80,
        "wires": [
            [
                "1344fe902f63e33b",
                "d5a4cbd916afc07e",
                "b8158ccc2a3d01d2"
            ]
        ]
    },
    {
        "id": "1344fe902f63e33b",
        "type": "debug",
        "z": "27223b680e789dbf",
        "name": "debug 1",
        "active": false,
        "tosidebar": true,
        "console": false,
        "tostatus": false,
        "complete": "false",
        "statusVal": "",
        "statusType": "auto",
        "x": 480,
        "y": 80,
        "wires": []
    },
    {
        "id": "d5a4cbd916afc07e",
        "type": "function",
        "z": "27223b680e789dbf",
        "name": "To AWS",
        "func": "let mas = msg.payload; \n\nmsg.payload = { \n    deviceId: \"1\",\n    temp: mas.temperature,\n    humidity: mas.humidity,\n    timestamp: Date.now().toString() \n       };\n       \nmsg.topic = \"sensor/\" + msg.payload.deviceId + \"/telemetry\"; \n\nreturn msg;",
        "outputs": 1,
        "timeout": 0,
        "noerr": 0,
        "initialize": "",
        "finalize": "",
        "libs": [],
        "x": 400,
        "y": 160,
        "wires": [
            [
                "b06b81fafc875af4"
            ]
        ]
    },
    {
        "id": "3cadfb6b3bd94ead",
        "type": "mqtt in",
        "z": "27223b680e789dbf",
        "name": "",
        "topic": "control_led/1",
        "qos": "0",
        "datatype": "auto-detect",
        "broker": "d2d8fad3a7e40e0d",
        "nl": false,
        "rap": true,
        "rh": 0,
        "inputs": 0,
        "x": 150,
        "y": 380,
        "wires": [
            [
                "ee22784c3b1ee811",
                "9303e34c7595370e"
            ]
        ]
    },
    {
        "id": "8cf302a8fd0c1191",
        "type": "mqtt out",
        "z": "27223b680e789dbf",
        "name": "",
        "topic": "esp32/control",
        "qos": "",
        "retain": "",
        "respTopic": "",
        "contentType": "",
        "userProps": "",
        "correl": "",
        "expiry": "",
        "broker": "355e398b737d8c0a",
        "x": 460,
        "y": 460,
        "wires": []
    },
    {
        "id": "ee22784c3b1ee811",
        "type": "debug",
        "z": "27223b680e789dbf",
        "name": "debug 2",
        "active": true,
        "tosidebar": true,
        "console": false,
        "tostatus": false,
        "complete": "false",
        "statusVal": "",
        "statusType": "auto",
        "x": 340,
        "y": 380,
        "wires": []
    },
    {
        "id": "a852dd859306a67a",
        "type": "influxdb out",
        "z": "27223b680e789dbf",
        "influxdb": "e0591f420dbe5264",
        "name": "to influx",
        "measurement": "",
        "precision": "",
        "retentionPolicy": "",
        "database": "database",
        "precisionV18FluxV20": "ms",
        "retentionPolicyV18Flux": "",
        "org": "local",
        "bucket": "monitor_temp",
        "x": 620,
        "y": 240,
        "wires": []
    },
    {
        "id": "b8158ccc2a3d01d2",
        "type": "function",
        "z": "27223b680e789dbf",
        "name": "To influxdb",
        "func": "let mas = msg.payload;\n\nmsg.measurement = \"temp/h/bucket\";   // اسم الجدول (bucket) في InfluxDB\n\n// هذه هي القيم التي ستُسجَّل داخل InfluxDB كحقول Fields\nmsg.payload = {\n    temp: mas.temperature,\n    humidity: mas.humidity,\n    timestamp: Date.now()\n};\n\n// ممكن تضيف Tags مثل deviceId\nmsg.tags = {\n    deviceId: \"1\"\n};\n\nreturn msg;\n",
        "outputs": 1,
        "timeout": 0,
        "noerr": 0,
        "initialize": "",
        "finalize": "",
        "libs": [],
        "x": 390,
        "y": 240,
        "wires": [
            [
                "a852dd859306a67a"
            ]
        ]
    },
    {
        "id": "b06b81fafc875af4",
        "type": "mqtt out",
        "z": "27223b680e789dbf",
        "name": "",
        "topic": "",
        "qos": "",
        "retain": "",
        "respTopic": "",
        "contentType": "",
        "userProps": "",
        "correl": "",
        "expiry": "",
        "broker": "d2d8fad3a7e40e0d",
        "x": 570,
        "y": 160,
        "wires": []
    },
    {
        "id": "9303e34c7595370e",
        "type": "function",
        "z": "27223b680e789dbf",
        "name": "To influxdb",
        "func": "let mas = msg.payload;\n\n\nmsg.payload = mas.led;\n\n\nreturn msg;\n",
        "outputs": 1,
        "timeout": 0,
        "noerr": 0,
        "initialize": "",
        "finalize": "",
        "libs": [],
        "x": 250,
        "y": 460,
        "wires": [
            [
                "8cf302a8fd0c1191"
            ]
        ]
    },
    {
        "id": "355e398b737d8c0a",
        "type": "mqtt-broker",
        "name": "wokwi server",
        "broker": "test.mosquitto.org",
        "port": 1883,
        "clientid": "",
        "autoConnect": true,
        "usetls": false,
        "protocolVersion": 4,
        "keepalive": 60,
        "cleansession": true,
        "autoUnsubscribe": true,
        "birthTopic": "",
        "birthQos": "0",
        "birthRetain": "false",
        "birthPayload": "",
        "birthMsg": {},
        "closeTopic": "",
        "closeQos": "0",
        "closeRetain": "false",
        "closePayload": "",
        "closeMsg": {},
        "willTopic": "",
        "willQos": "0",
        "willRetain": "false",
        "willPayload": "",
        "willMsg": {},
        "userProps": "",
        "sessionExpiry": ""
    },
    {
        "id": "d2d8fad3a7e40e0d",
        "type": "mqtt-broker",
        "name": "aws_server",
        "broker": "a16yla8r2d4dg4-ats.iot.us-east-2.amazonaws.com",
        "port": "8883",
        "tls": "c54a4d5ad4ba631c",
        "clientid": "",
        "autoConnect": true,
        "usetls": true,
        "protocolVersion": 4,
        "keepalive": 60,
        "cleansession": true,
        "autoUnsubscribe": true,
        "birthTopic": "",
        "birthQos": "0",
        "birthRetain": "false",
        "birthPayload": "",
        "birthMsg": {},
        "closeTopic": "",
        "closeQos": "0",
        "closeRetain": "false",
        "closePayload": "",
        "closeMsg": {},
        "willTopic": "",
        "willQos": "0",
        "willRetain": "false",
        "willPayload": "",
        "willMsg": {},
        "userProps": "",
        "sessionExpiry": ""
    },
    {
        "id": "e0591f420dbe5264",
        "type": "influxdb",
        "hostname": "127.0.0.1",
        "port": 8086,
        "protocol": "http",
        "database": "database",
        "name": "",
        "usetls": false,
        "tls": "",
        "influxdbVersion": "2.0",
        "url": "http://localhost:8086",
        "timeout": 10,
        "rejectUnauthorized": true
    },
    {
        "id": "c54a4d5ad4ba631c",
        "type": "tls-config",
        "name": "",
        "cert": "",
        "key": "",
        "ca": "",
        "certname": "961b77c8106ff3c8015844df42731b076f0866dd2e7f63e8e6a372bc1db230ab-certificate.pem.crt",
        "keyname": "961b77c8106ff3c8015844df42731b076f0866dd2e7f63e8e6a372bc1db230ab-private.pem.key",
        "caname": "AmazonRootCA1.pem",
        "servername": "",
        "verifyservercert": true,
        "alpnprotocol": ""
    },
    {
        "id": "cf42293362ed59de",
        "type": "global-config",
        "env": [],
        "modules": {
            "node-red-contrib-influxdb": "0.7.0"
        }
    }
]